{
  "firstLayout": "MenuInicio",
  "gdVersion": {
    "build": 99,
    "major": 4,
    "minor": 0,
    "revision": 0
  },
  "properties": {
    "adaptGameResolutionAtRuntime": true,
    "antialiasingMode": "MSAA",
    "antialisingEnabledOnMobile": false,
    "folderProject": true,
    "orientation": "landscape",
    "packageName": "com.example.gamename",
    "pixelsRounding": false,
    "projectUuid": "e75b1442-ac31-43af-a2e5-01fcb37d31bb",
    "scaleMode": "linear",
    "sizeOnStartupMode": "adaptWidth",
    "templateSlug": "",
    "useExternalSourceFiles": false,
    "version": "1.0.0",
    "name": "Pampa02",
    "description": "",
    "author": "",
    "windowWidth": 1280,
    "windowHeight": 720,
    "latestCompilationDirectory": "",
    "maxFPS": 60,
    "minFPS": 20,
    "verticalSync": false,
    "platformSpecificAssets": {},
    "loadingScreen": {
      "backgroundColor": 0,
      "backgroundFadeInDuration": 0.2,
      "backgroundImageResourceName": "",
      "gdevelopLogoStyle": "light",
      "logoAndProgressFadeInDuration": 0.2,
      "logoAndProgressLogoFadeInDelay": 0.2,
      "minDuration": 1.5,
      "progressBarColor": 16777215,
      "progressBarHeight": 20,
      "progressBarMaxWidth": 200,
      "progressBarMinWidth": 40,
      "progressBarWidthPercent": 30,
      "showGDevelopSplash": true,
      "showProgressBar": true
    },
    "watermark": {
      "placement": "bottom-left",
      "showWatermark": false
    },
    "authorIds": [],
    "authorUsernames": [],
    "categories": [],
    "playableDevices": [],
    "extensionProperties": [],
    "platforms": [
      {
        "name": "GDevelop JS platform"
      }
    ],
    "currentPlatform": "GDevelop JS platform"
  },
  "resources": {
    "resources": [
      {
        "alwaysLoaded": false,
        "file": "assets/cubo1.png",
        "kind": "image",
        "metadata": "{\"extension\":\".png\"}",
        "name": "cubo1",
        "smoothed": true,
        "userAdded": true
      },
      {
        "alwaysLoaded": false,
        "file": "_76225909-9624-4c3e-9a0f-ef1b3390c059.jpg",
        "kind": "image",
        "metadata": "",
        "name": "_76225909-9624-4c3e-9a0f-ef1b3390c059.jpg",
        "smoothed": true,
        "userAdded": false
      },
      {
        "alwaysLoaded": false,
        "file": "assets/Yellow Button_Hovered.png",
        "kind": "image",
        "metadata": "",
        "name": "Yellow Button_Hovered.png",
        "smoothed": true,
        "userAdded": false,
        "origin": {
          "identifier": "https://asset-resources.gdevelop.io/public-resources/Menu buttons/c1e14acb64b9963341656c997853154dc4c86cd1c46fb12bfbe012d99712ef61_Yellow Button_Hovered.png",
          "name": "Yellow Button_Hovered.png"
        }
      },
      {
        "alwaysLoaded": false,
        "file": "assets/Yellow Button_Idle.png",
        "kind": "image",
        "metadata": "",
        "name": "Yellow Button_Idle.png",
        "smoothed": true,
        "userAdded": false,
        "origin": {
          "identifier": "https://asset-resources.gdevelop.io/public-resources/Menu buttons/1cacfd123a1eb708837337c27982f6871f5127c5890dbf0775e0f411958fcbf1_Yellow Button_Idle.png",
          "name": "Yellow Button_Idle.png"
        }
      },
      {
        "alwaysLoaded": false,
        "file": "assets/Yellow Button_Pressed.png",
        "kind": "image",
        "metadata": "",
        "name": "Yellow Button_Pressed.png",
        "smoothed": true,
        "userAdded": false,
        "origin": {
          "identifier": "https://asset-resources.gdevelop.io/public-resources/Menu buttons/928c3ea4db1da835c9f8cc5b7089a47228350209d2ff489e1484c31e5ce41b3d_Yellow Button_Pressed.png",
          "name": "Yellow Button_Pressed.png"
        }
      },
      {
        "file": "Super Milk.ttf",
        "kind": "font",
        "metadata": "",
        "name": "Super Milk.ttf",
        "userAdded": true
      },
      {
        "file": "select_004.ogg",
        "kind": "audio",
        "metadata": "",
        "name": "select_004.ogg",
        "preloadAsMusic": false,
        "preloadAsSound": false,
        "preloadInCache": false,
        "userAdded": true
      },
      {
        "alwaysLoaded": false,
        "file": "assets/NewSprite.png",
        "kind": "image",
        "metadata": "{\"extension\":\".png\"}",
        "name": "NewSprite",
        "smoothed": true,
        "userAdded": true
      },
      {
        "alwaysLoaded": false,
        "file": "assets/NewSprite2.png",
        "kind": "image",
        "metadata": "{\"extension\":\".png\"}",
        "name": "NewSprite2",
        "smoothed": true,
        "userAdded": false
      },
      {
        "alwaysLoaded": false,
        "file": "assets/Small Plastic Green Round Switch_Off.png",
        "kind": "image",
        "metadata": "",
        "name": "Small Plastic Green Round Switch_Off.png",
        "smoothed": true,
        "userAdded": false,
        "origin": {
          "identifier": "https://asset-resources.gdevelop.io/public-resources/Settings UI/Toggle Switch/80b157db1711ebc0166b1e42ff29bbf8837b5c9a0b1d62494e8eb5ca06837a31_Small Plastic Green Round Switch_Off.png",
          "name": "Small Plastic Green Round Switch_Off.png"
        }
      },
      {
        "alwaysLoaded": false,
        "file": "assets/Small Plastic Green Round Switch_On.png",
        "kind": "image",
        "metadata": "",
        "name": "Small Plastic Green Round Switch_On.png",
        "smoothed": true,
        "userAdded": false,
        "origin": {
          "identifier": "https://asset-resources.gdevelop.io/public-resources/Settings UI/Toggle Switch/0af9e04c0c382482aeeaa36bc713a626249d6f6df3280bbccc6a042973ad555c_Small Plastic Green Round Switch_On.png",
          "name": "Small Plastic Green Round Switch_On.png"
        }
      },
      {
        "alwaysLoaded": false,
        "file": "assets/Green Button_Hovered.png",
        "kind": "image",
        "metadata": "",
        "name": "Green Button_Hovered.png",
        "smoothed": true,
        "userAdded": false,
        "origin": {
          "identifier": "https://asset-resources.gdevelop.io/public-resources/Menu buttons/bff6adc488c7379b21ceba34e9104e861791b2fbb54b4aae167fe90115b92fa3_Green Button_Hovered.png",
          "name": "Green Button_Hovered.png"
        }
      },
      {
        "alwaysLoaded": false,
        "file": "assets/Green Button_Idle.png",
        "kind": "image",
        "metadata": "",
        "name": "Green Button_Idle.png",
        "smoothed": true,
        "userAdded": false,
        "origin": {
          "identifier": "https://asset-resources.gdevelop.io/public-resources/Menu buttons/f46d20e99495562ee66ee2f26defdb0788588184bd30b1f7b951ae728ce63d2a_Green Button_Idle.png",
          "name": "Green Button_Idle.png"
        }
      },
      {
        "alwaysLoaded": false,
        "file": "assets/Green Button_Pressed.png",
        "kind": "image",
        "metadata": "",
        "name": "Green Button_Pressed.png",
        "smoothed": true,
        "userAdded": false,
        "origin": {
          "identifier": "https://asset-resources.gdevelop.io/public-resources/Menu buttons/ecb33703984d3107196efce7335025d7ec104351fe8cdeb581c73fe0b8038c34_Green Button_Pressed.png",
          "name": "Green Button_Pressed.png"
        }
      },
      {
        "alwaysLoaded": false,
        "file": "assets/NewSprite3.png",
        "kind": "image",
        "metadata": "{\"extension\":\".png\",\"localFilePath\":\"assets/NewSprite3.png\"}",
        "name": "NewSprite3",
        "smoothed": true,
        "userAdded": true
      },
      {
        "file": "switch_007.ogg",
        "kind": "audio",
        "metadata": "",
        "name": "switch_007.ogg",
        "preloadAsMusic": false,
        "preloadAsSound": false,
        "preloadInCache": false,
        "userAdded": true
      },
      {
        "alwaysLoaded": false,
        "file": "cubo_nro_no_sombra_si.png",
        "kind": "image",
        "metadata": "",
        "name": "cubo_nro_no_sombra_si.png",
        "smoothed": true,
        "userAdded": true
      },
      {
        "alwaysLoaded": false,
        "file": "bola_nro_no_sombra_si.png",
        "kind": "image",
        "metadata": "",
        "name": "bola_nro_no_sombra_si.png",
        "smoothed": true,
        "userAdded": true
      },
      {
        "alwaysLoaded": false,
        "file": "bola_nro_no_sombra_no.png",
        "kind": "image",
        "metadata": "",
        "name": "bola_nro_no_sombra_no.png",
        "smoothed": true,
        "userAdded": true
      },
      {
        "alwaysLoaded": false,
        "file": "bola_nro_no_sombra_si2.png",
        "kind": "image",
        "metadata": "",
        "name": "bola_nro_no_sombra_si2.png",
        "smoothed": true,
        "userAdded": true
      },
      {
        "alwaysLoaded": false,
        "file": "assets/Retry.png",
        "kind": "image",
        "metadata": "",
        "name": "Retry.png",
        "smoothed": true,
        "userAdded": false,
        "origin": {
          "identifier": "https://asset-resources.gdevelop.io/public-resources/Interface/Casual Buttons Pack/cc0cb4e9134b2f362d8145f10a42d356d3f10bb6e432187d81c25f164099812c_Retry.png",
          "name": "Retry.png"
        }
      },
      {
        "alwaysLoaded": false,
        "file": "assets/pausa.png",
        "kind": "image",
        "metadata": "{\"extension\":\".png\",\"localFilePath\":\"assets/pausa.png\"}",
        "name": "pausa",
        "smoothed": true,
        "userAdded": true
      }
    ],
    "resourceFolders": []
  },
  "objects": [
    {
      "adaptCollisionMaskAutomatically": true,
      "assetStoreId": "",
      "name": "jugador",
      "type": "Sprite",
      "updateIfNotVisible": false,
      "variables": [
        {
          "folded": true,
          "name": "SumaTotal",
          "type": "number",
          "value": 0
        },
        {
          "name": "Objetivo",
          "type": "number",
          "value": 0
        }
      ],
      "effects": [],
      "behaviors": [
        {
          "deceleration": 100000,
          "name": "TopDownMovement",
          "type": "TopDownMovementBehavior::TopDownMovementBehavior",
          "allowDiagonals": false,
          "maxSpeed": 400,
          "acceleration": 600,
          "angleOffset": 0,
          "angularMaxSpeed": 180,
          "customIsometryAngle": 30,
          "ignoreDefaultControls": true,
          "movementAngleOffset": 0,
          "rotateObject": false,
          "viewpoint": "TopDown"
        }
      ],
      "animations": [
        {
          "name": "",
          "useMultipleDirections": false,
          "directions": [
            {
              "looping": false,
              "timeBetweenFrames": 0.08,
              "sprites": [
                {
                  "hasCustomCollisionMask": true,
                  "image": "cubo_nro_no_sombra_si.png",
                  "points": [],
                  "originPoint": {
                    "name": "origine",
                    "x": 24.5,
                    "y": 19
                  },
                  "centerPoint": {
                    "automatic": false,
                    "name": "centre",
                    "x": 24.5,
                    "y": 19
                  },
                  "customCollisionMask": [
                    [
                      {
                        "x": 2,
                        "y": 2
                      },
                      {
                        "x": 59,
                        "y": 2
                      },
                      {
                        "x": 59,
                        "y": 59
                      },
                      {
                        "x": 2,
                        "y": 59
                      }
                    ]
                  ]
                }
              ]
            }
          ]
        }
      ]
    },
    {
      "assetStoreId": "99f912de1cf5033ae934a8453c2f98a712955bcdb5ea1b1fda2fe2aa616de4a9",
      "name": "SmallGreenPlasticRoundSwitch",
      "type": "SpriteToggleSwitch::SpriteToggleSwitch",
      "variables": [],
      "effects": [],
      "behaviors": [],
      "content": {},
      "childrenContent": {
        "State": {
          "adaptCollisionMaskAutomatically": false,
          "updateIfNotVisible": false,
          "animations": [
            {
              "name": "Unchecked",
              "useMultipleDirections": false,
              "directions": [
                {
                  "looping": false,
                  "timeBetweenFrames": 0.08,
                  "sprites": [
                    {
                      "hasCustomCollisionMask": false,
                      "image": "Small Plastic Green Round Switch_Off.png",
                      "points": [],
                      "originPoint": {
                        "name": "origine",
                        "x": 0,
                        "y": 0
                      },
                      "centerPoint": {
                        "automatic": true,
                        "name": "centre",
                        "x": 0,
                        "y": 0
                      },
                      "customCollisionMask": []
                    }
                  ]
                }
              ]
            },
            {
              "name": "Checked",
              "useMultipleDirections": false,
              "directions": [
                {
                  "looping": false,
                  "timeBetweenFrames": 0.08,
                  "sprites": [
                    {
                      "hasCustomCollisionMask": false,
                      "image": "Small Plastic Green Round Switch_On.png",
                      "points": [],
                      "originPoint": {
                        "name": "origine",
                        "x": 0,
                        "y": 0
                      },
                      "centerPoint": {
                        "automatic": true,
                        "name": "centre",
                        "x": 0,
                        "y": 0
                      },
                      "customCollisionMask": []
                    }
                  ]
                }
              ]
            }
          ]
        }
      }
    },
    {
      "assetStoreId": "",
      "bold": false,
      "italic": false,
      "name": "Pausamusica",
      "smoothed": true,
      "type": "TextObject::Text",
      "underlined": false,
      "variables": [],
      "effects": [
        {
          "effectType": "Glow",
          "name": "Effect",
          "doubleParameters": {
            "distance": 15,
            "innerStrength": 1,
            "outerStrength": 2
          },
          "stringParameters": {
            "color": "255;255;255"
          },
          "booleanParameters": {}
        }
      ],
      "behaviors": [],
      "string": "SONIDO",
      "font": "Super Milk.ttf",
      "textAlignment": "left",
      "characterSize": 40,
      "color": {
        "b": 0,
        "g": 0,
        "r": 0
      }
    },
    {
      "assetStoreId": "b44dba91245ff1ac84a7b450e078194f19321d135fd8a67cd19bc9cb3403fba5",
      "name": "SALIR",
      "type": "PanelSpriteButton::PanelSpriteButton",
      "variables": [],
      "effects": [],
      "behaviors": [],
      "content": {
        "LeftPadding": 16,
        "RightPadding": 16,
        "PressedLabelOffsetY": 10,
        "BottomPadding": 32,
        "TopPadding": 16,
        "HoveredFadeOutDuration": 0.25
      },
      "childrenContent": {
        "Hovered": {
          "bottomMargin": 32,
          "height": 106,
          "leftMargin": 16,
          "rightMargin": 16,
          "texture": "Green Button_Hovered.png",
          "tiled": true,
          "topMargin": 16,
          "width": 256
        },
        "Idle": {
          "bottomMargin": 32,
          "height": 106,
          "leftMargin": 16,
          "rightMargin": 16,
          "texture": "Green Button_Idle.png",
          "tiled": true,
          "topMargin": 16,
          "width": 256
        },
        "Label": {
          "bold": false,
          "italic": false,
          "smoothed": true,
          "underlined": false,
          "string": "SALIR",
          "font": "",
          "textAlignment": "center",
          "characterSize": 60,
          "color": {
            "b": 29,
            "g": 99,
            "r": 62
          }
        },
        "Pressed": {
          "bottomMargin": 16,
          "height": 106,
          "leftMargin": 16,
          "rightMargin": 16,
          "texture": "Green Button_Pressed.png",
          "tiled": true,
          "topMargin": 32,
          "width": 256
        }
      }
    },
    {
      "adaptCollisionMaskAutomatically": true,
      "assetStoreId": "",
      "name": "pausa",
      "type": "Sprite",
      "updateIfNotVisible": false,
      "variables": [],
      "effects": [],
      "behaviors": [],
      "animations": [
        {
          "name": "pausa",
          "useMultipleDirections": false,
          "directions": [
            {
              "looping": false,
              "metadata": "{\"pskl\":{}}",
              "timeBetweenFrames": 0.08,
              "sprites": [
                {
                  "hasCustomCollisionMask": true,
                  "image": "pausa",
                  "points": [],
                  "originPoint": {
                    "name": "origine",
                    "x": 0,
                    "y": 0
                  },
                  "centerPoint": {
                    "automatic": true,
                    "name": "centre",
                    "x": 0,
                    "y": 0
                  },
                  "customCollisionMask": [
                    [
                      {
                        "x": 0,
                        "y": 0
                      },
                      {
                        "x": 64,
                        "y": 0
                      },
                      {
                        "x": 64,
                        "y": 64
                      },
                      {
                        "x": 0,
                        "y": 64
                      }
                    ]
                  ]
                }
              ]
            }
          ]
        }
      ]
    },
    {
      "assetStoreId": "",
      "bold": false,
      "italic": false,
      "name": "Pausa",
      "smoothed": true,
      "type": "TextObject::Text",
      "underlined": false,
      "variables": [],
      "effects": [
        {
          "effectType": "Glow",
          "name": "Effect",
          "doubleParameters": {
            "distance": 15,
            "innerStrength": 1,
            "outerStrength": 10
          },
          "stringParameters": {
            "color": "255;255;255"
          },
          "booleanParameters": {}
        }
      ],
      "behaviors": [],
      "string": "PAUSA",
      "font": "Super Milk.ttf",
      "textAlignment": "left",
      "characterSize": 200,
      "color": {
        "b": 0,
        "g": 0,
        "r": 0
      }
    },
    {
      "adaptCollisionMaskAutomatically": true,
      "assetStoreId": "",
      "name": "cover",
      "type": "Sprite",
      "updateIfNotVisible": false,
      "variables": [],
      "effects": [],
      "behaviors": [],
      "animations": [
        {
          "name": "NewSprite",
          "useMultipleDirections": false,
          "directions": [
            {
              "looping": false,
              "metadata": "{\"pskl\":{}}",
              "timeBetweenFrames": 0.08,
              "sprites": [
                {
                  "hasCustomCollisionMask": true,
                  "image": "NewSprite2",
                  "points": [],
                  "originPoint": {
                    "name": "origine",
                    "x": 0,
                    "y": 0
                  },
                  "centerPoint": {
                    "automatic": true,
                    "name": "centre",
                    "x": 0,
                    "y": 0
                  },
                  "customCollisionMask": [
                    [
                      {
                        "x": 0,
                        "y": 0
                      },
                      {
                        "x": 64,
                        "y": 0
                      },
                      {
                        "x": 64,
                        "y": 64
                      },
                      {
                        "x": 0,
                        "y": 64
                      }
                    ]
                  ]
                }
              ]
            }
          ]
        }
      ]
    },
    {
      "adaptCollisionMaskAutomatically": true,
      "assetStoreId": "",
      "name": "recolectable",
      "type": "Sprite",
      "updateIfNotVisible": false,
      "variables": [
        {
          "folded": true,
          "name": "aporte",
          "type": "number",
          "value": 0
        }
      ],
      "effects": [],
      "behaviors": [],
      "animations": [
        {
          "name": "",
          "useMultipleDirections": false,
          "directions": [
            {
              "looping": false,
              "timeBetweenFrames": 0.08,
              "sprites": [
                {
                  "hasCustomCollisionMask": true,
                  "image": "bola_nro_no_sombra_si.png",
                  "points": [],
                  "originPoint": {
                    "name": "origine",
                    "x": 24.5,
                    "y": 19
                  },
                  "centerPoint": {
                    "automatic": false,
                    "name": "centre",
                    "x": 24.5,
                    "y": 19
                  },
                  "customCollisionMask": [
                    [
                      {
                        "x": 2,
                        "y": 3
                      },
                      {
                        "x": 58,
                        "y": 3
                      },
                      {
                        "x": 58,
                        "y": 58
                      },
                      {
                        "x": 2,
                        "y": 58
                      }
                    ]
                  ]
                }
              ]
            }
          ]
        }
      ]
    },
    {
      "adaptCollisionMaskAutomatically": true,
      "assetStoreId": "",
      "name": "sticky",
      "type": "Sprite",
      "updateIfNotVisible": false,
      "variables": [
        {
          "folded": true,
          "name": "aporte",
          "type": "number",
          "value": 0
        }
      ],
      "effects": [],
      "behaviors": [],
      "animations": [
        {
          "name": "",
          "useMultipleDirections": false,
          "directions": [
            {
              "looping": false,
              "timeBetweenFrames": 0.08,
              "sprites": [
                {
                  "hasCustomCollisionMask": true,
                  "image": "bola_nro_no_sombra_no.png",
                  "points": [],
                  "originPoint": {
                    "name": "origine",
                    "x": 24.5,
                    "y": 19
                  },
                  "centerPoint": {
                    "automatic": false,
                    "name": "centre",
                    "x": 24.5,
                    "y": 19
                  },
                  "customCollisionMask": [
                    [
                      {
                        "x": 2,
                        "y": 3
                      },
                      {
                        "x": 58,
                        "y": 3
                      },
                      {
                        "x": 58,
                        "y": 58
                      },
                      {
                        "x": 2,
                        "y": 58
                      }
                    ]
                  ]
                }
              ]
            }
          ]
        }
      ]
    },
    {
      "assetStoreId": "",
      "bold": true,
      "italic": false,
      "name": "Objetivo",
      "smoothed": true,
      "type": "TextObject::Text",
      "underlined": false,
      "variables": [],
      "effects": [],
      "behaviors": [],
      "string": "Alcanza:",
      "font": "Super Milk.ttf",
      "textAlignment": "left",
      "characterSize": 60,
      "color": {
        "b": 226,
        "g": 144,
        "r": 74
      }
    },
    {
      "assetStoreId": "",
      "bold": false,
      "italic": false,
      "name": "AporteObjeto",
      "smoothed": true,
      "type": "TextObject::Text",
      "underlined": false,
      "variables": [],
      "effects": [],
      "behaviors": [],
      "string": "aporte",
      "font": "",
      "textAlignment": "left",
      "characterSize": 20,
      "color": {
        "b": 0,
        "g": 0,
        "r": 0
      }
    },
    {
      "assetStoreId": "",
      "bold": false,
      "italic": false,
      "name": "PlayerValue",
      "smoothed": true,
      "type": "TextObject::Text",
      "underlined": false,
      "variables": [],
      "effects": [],
      "behaviors": [],
      "string": "Suma",
      "font": "",
      "textAlignment": "left",
      "characterSize": 20,
      "color": {
        "b": 0,
        "g": 0,
        "r": 0
      }
    },
    {
      "assetStoreId": "b44dba91245ff1ac84a7b450e078194f19321d135fd8a67cd19bc9cb3403fba5",
      "name": "Reiniciar",
      "type": "PanelSpriteButton::PanelSpriteButton",
      "variables": [],
      "effects": [],
      "behaviors": [],
      "content": {
        "LeftPadding": 16,
        "RightPadding": 16,
        "PressedLabelOffsetY": 10,
        "BottomPadding": 32,
        "TopPadding": 16,
        "HoveredFadeOutDuration": 0.25
      },
      "childrenContent": {
        "Hovered": {
          "bottomMargin": 32,
          "height": 106,
          "leftMargin": 16,
          "rightMargin": 16,
          "texture": "Green Button_Hovered.png",
          "tiled": true,
          "topMargin": 16,
          "width": 256
        },
        "Idle": {
          "bottomMargin": 32,
          "height": 106,
          "leftMargin": 16,
          "rightMargin": 16,
          "texture": "Green Button_Idle.png",
          "tiled": true,
          "topMargin": 16,
          "width": 256
        },
        "Label": {
          "bold": true,
          "italic": false,
          "smoothed": true,
          "underlined": false,
          "string": "REINICIAR",
          "font": "",
          "textAlignment": "center",
          "characterSize": 40,
          "color": {
            "b": 29,
            "g": 99,
            "r": 62
          }
        },
        "Pressed": {
          "bottomMargin": 16,
          "height": 106,
          "leftMargin": 16,
          "rightMargin": 16,
          "texture": "Green Button_Pressed.png",
          "tiled": true,
          "topMargin": 32,
          "width": 256
        }
      }
    },
    {
      "adaptCollisionMaskAutomatically": true,
      "assetStoreId": "",
      "name": "perdiste",
      "type": "Sprite",
      "updateIfNotVisible": false,
      "variables": [],
      "effects": [],
      "behaviors": [],
      "animations": [
        {
          "name": "NewSprite",
          "useMultipleDirections": false,
          "directions": [
            {
              "looping": false,
              "metadata": "{\"pskl\":{}}",
              "timeBetweenFrames": 0.08,
              "sprites": [
                {
                  "hasCustomCollisionMask": true,
                  "image": "NewSprite3",
                  "points": [],
                  "originPoint": {
                    "name": "origine",
                    "x": 0,
                    "y": 0
                  },
                  "centerPoint": {
                    "automatic": true,
                    "name": "centre",
                    "x": 0,
                    "y": 0
                  },
                  "customCollisionMask": [
                    [
                      {
                        "x": 0,
                        "y": 0
                      },
                      {
                        "x": 64,
                        "y": 0
                      },
                      {
                        "x": 64,
                        "y": 64
                      },
                      {
                        "x": 0,
                        "y": 64
                      }
                    ]
                  ]
                }
              ]
            }
          ]
        }
      ]
    },
    {
      "assetStoreId": "",
      "bold": false,
      "italic": false,
      "name": "game_over",
      "smoothed": true,
      "type": "TextObject::Text",
      "underlined": false,
      "variables": [],
      "effects": [
        {
          "effectType": "Glow",
          "name": "Effect",
          "doubleParameters": {
            "distance": 15,
            "innerStrength": 1,
            "outerStrength": 2
          },
          "stringParameters": {
            "color": "255;255;255"
          },
          "booleanParameters": {}
        }
      ],
      "behaviors": [],
      "string": "PERDISTE",
      "font": "Super Milk.ttf",
      "textAlignment": "left",
      "characterSize": 200,
      "color": {
        "b": 0,
        "g": 0,
        "r": 0
      }
    }
  ],
  "objectsFolderStructure": {
    "folderName": "__ROOT",
    "children": [
      {
        "objectName": "jugador"
      },
      {
        "objectName": "SmallGreenPlasticRoundSwitch"
      },
      {
        "objectName": "Pausamusica"
      },
      {
        "objectName": "Pausa"
      },
      {
        "objectName": "SALIR"
      },
      {
        "objectName": "pausa"
      },
      {
        "objectName": "perdiste"
      },
      {
        "objectName": "cover"
      },
      {
        "objectName": "recolectable"
      },
      {
        "objectName": "sticky"
      },
      {
        "objectName": "Objetivo"
      },
      {
        "objectName": "AporteObjeto"
      },
      {
        "objectName": "PlayerValue"
      },
      {
        "objectName": "Reiniciar"
      },
      {
        "objectName": "game_over"
      }
    ]
  },
  "objectsGroups": [],
  "variables": [
    {
      "folded": true,
      "name": "Pausa",
      "type": "number",
      "value": 0
    }
  ],
  "layouts": [
    {
      "__REFERENCE_TO_SPLIT_OBJECT": true,
      "referenceTo": "/layouts/menuinicio"
    },
    {
      "__REFERENCE_TO_SPLIT_OBJECT": true,
      "referenceTo": "/layouts/nivel1"
    },
    {
      "__REFERENCE_TO_SPLIT_OBJECT": true,
      "referenceTo": "/layouts/nivel2"
    }
  ],
  "externalEvents": [],
  "eventsFunctionsExtensions": [
    {
      "__REFERENCE_TO_SPLIT_OBJECT": true,
      "referenceTo": "/eventsFunctionsExtensions/sticker"
    },
    {
      "__REFERENCE_TO_SPLIT_OBJECT": true,
      "referenceTo": "/eventsFunctionsExtensions/spritetoggleswitch"
    },
    {
      "__REFERENCE_TO_SPLIT_OBJECT": true,
      "referenceTo": "/eventsFunctionsExtensions/panelspritebutton"
    }
  ],
  "externalLayouts": [],
  "externalSourceFiles": []
}